{"connectedPlayers":[{"c":2903,"p":"1"},{"p":"0","c":1588},{"c":1067,"p":"2"},{"c":651,"p":"0"},{"c":589,"p":"3"},{"p":"4","c":426},{"c":270,"p":"5"},{"c":199,"p":"6"},{"p":"7","c":133},{"p":"8","c":94},{"p":"9","c":50},{"p":"10","c":47},{"c":26,"p":"12"},{"p":"11","c":26},{"c":18,"p":"13"},{"c":7,"p":"14"},{"p":"17","c":6},{"p":"16","c":3},{"p":"15","c":3},{"c":2,"p":"18"},{"p":"32","c":1},{"p":"30","c":1},{"p":"23","c":1},{"p":"22","c":1},{"c":1,"p":"19"}],"players":[{"p":127,"d":"2024-04-11"},{"d":"2024-04-12","p":50},{"d":"2024-04-13","p":925},{"d":"2024-04-14","p":1838},{"d":"2024-04-15","p":3339},{"p":4696,"d":"2024-04-16"},{"p":6497,"d":"2024-04-17"},{"p":7871,"d":"2024-04-18"},{"d":"2024-04-19","p":9016},{"d":"2024-04-20","p":10086},{"p":11382,"d":"2024-04-21"},{"d":"2024-04-22","p":12499},{"p":13333,"d":"2024-04-23"},{"p":14261,"d":"2024-04-24"},{"p":14916,"d":"2024-04-25"}],"versions":[{"c":37,"d":"2024-04-11","v":"8.5.1"},{"d":"2024-04-11","v":"9.0.0","c":7},{"v":"All","d":"2024-04-11","c":44},{"c":61,"v":"8.5.1","d":"2024-04-12"},{"c":18,"v":"9.0.0","d":"2024-04-12"},{"v":"8.5.0","d":"2024-04-12","c":1},{"v":"All","d":"2024-04-12","c":80},{"v":"8.5.1","d":"2024-04-13","c":201},{"d":"2024-04-13","v":"9.0.0","c":75},{"d":"2024-04-13","v":"8.5.0","c":1},{"c":277,"v":"All","d":"2024-04-13"},{"c":453,"v":"8.5.1","d":"2024-04-14"},{"v":"9.0.0","d":"2024-04-14","c":154},{"c":2,"v":"8.5.0","d":"2024-04-14"},{"c":609,"d":"2024-04-14","v":"All"},{"d":"2024-04-15","v":"8.5.1","c":922},{"c":306,"d":"2024-04-15","v":"9.0.0"},{"c":73,"v":"8.5.2","d":"2024-04-15"},{"c":3,"v":"8.5.0","d":"2024-04-15"},{"d":"2024-04-15","v":"All","c":1304},{"c":1408,"v":"8.5.1","d":"2024-04-16"},{"c":345,"d":"2024-04-16","v":"9.0.0"},{"v":"8.5.2","d":"2024-04-16","c":251},{"v":"8.5.0","d":"2024-04-16","c":4},{"c":2008,"d":"2024-04-16","v":"All"},{"v":"8.5.1","d":"2024-04-17","c":2135},{"c":406,"d":"2024-04-17","v":"9.0.0"},{"v":"8.5.2","d":"2024-04-17","c":400},{"d":"2024-04-17","v":"8.5.0","c":7},{"d":"2024-04-17","v":"All","c":2948},{"c":2685,"d":"2024-04-18","v":"8.5.1"},{"v":"8.5.2","d":"2024-04-18","c":523},{"v":"9.0.0","d":"2024-04-18","c":458},{"d":"2024-04-18","v":"8.5.0","c":9},{"c":3675,"v":"All","d":"2024-04-18"},{"c":3173,"v":"8.5.1","d":"2024-04-19"},{"c":649,"v":"8.5.2","d":"2024-04-19"},{"c":487,"d":"2024-04-19","v":"9.0.0"},{"v":"8.5.0","d":"2024-04-19","c":13},{"v":"8.4.0","d":"2024-04-19","c":1},{"v":"All","d":"2024-04-19","c":4323},{"c":3629,"v":"8.5.1","d":"2024-04-20"},{"v":"8.5.2","d":"2024-04-20","c":759},{"d":"2024-04-20","v":"9.0.0","c":534},{"d":"2024-04-20","v":"8.5.0","c":19},{"c":1,"d":"2024-04-20","v":"8.4.0"},{"d":"2024-04-20","v":"All","c":4942},{"c":4194,"v":"8.5.1","d":"2024-04-21"},{"c":882,"v":"8.5.2","d":"2024-04-21"},{"v":"9.0.0","d":"2024-04-21","c":574},{"c":23,"d":"2024-04-21","v":"8.5.0"},{"v":"8.4.0","d":"2024-04-21","c":1},{"v":"All","d":"2024-04-21","c":5674},{"v":"8.5.1","d":"2024-04-22","c":4782},{"c":994,"d":"2024-04-22","v":"8.5.2"},{"c":608,"v":"9.0.0","d":"2024-04-22"},{"v":"8.5.0","d":"2024-04-22","c":31},{"v":"8.4.0","d":"2024-04-22","c":1},{"c":6416,"v":"All","d":"2024-04-22"},{"c":5267,"v":"8.5.1","d":"2024-04-23"},{"v":"8.5.2","d":"2024-04-23","c":1080},{"c":655,"d":"2024-04-23","v":"9.0.0"},{"c":31,"d":"2024-04-23","v":"8.5.0"},{"c":1,"d":"2024-04-23","v":"8.4.0"},{"c":7034,"v":"All","d":"2024-04-23"},{"c":5691,"v":"8.5.1","d":"2024-04-24"},{"d":"2024-04-24","v":"8.5.2","c":1145},{"c":690,"v":"9.0.0","d":"2024-04-24"},{"c":36,"d":"2024-04-24","v":"8.5.0"},{"c":2,"v":"8.4.0","d":"2024-04-24"},{"d":"2024-04-24","v":"All","c":7564},{"d":"2024-04-25","v":"8.5.1","c":6106},{"d":"2024-04-25","v":"8.5.2","c":1216},{"c":730,"v":"9.0.0","d":"2024-04-25"},{"c":40,"v":"8.5.0","d":"2024-04-25"},{"c":2,"v":"8.4.0","d":"2024-04-25"},{"c":8094,"d":"2024-04-25","v":"All"}],"countries":[{"c":"DE","i":2223},{"c":"US","i":1121},{"c":"GB","i":668},{"c":"NL","i":622},{"c":"FR","i":581},{"i":384,"c":"CH"},{"c":"SE","i":213},{"i":179,"c":"AT"},{"i":178,"c":"CA"},{"i":171,"c":"BE"},{"c":"IT","i":152},{"i":132,"c":"PL"},{"i":112,"c":"AU"},{"c":"NO","i":107},{"c":"DK","i":89},{"c":"RU","i":73},{"i":68,"c":"ES"},{"i":68,"c":"CN"},{"c":"JP","i":66},{"i":65,"c":"CZ"},{"c":"HU","i":59},{"i":55,"c":"RO"},{"i":55,"c":"FI"},{"i":49,"c":"NZ"},{"i":40,"c":"HK"},{"i":38,"c":"UA"},{"i":35,"c":"IE"},{"c":"TW","i":34},{"c":"PT","i":34},{"c":"GR","i":32},{"i":29,"c":"RS"},{"c":"KR","i":28},{"i":25,"c":"ZA"},{"i":25,"c":"SK"},{"i":23,"c":"SI"},{"i":18,"c":"SG"},{"c":"HR","i":16},{"c":"BG","i":15},{"i":14,"c":"IL"},{"c":"TH","i":13},{"c":"VN","i":12},{"c":"IN","i":12},{"i":12,"c":"CL"},{"i":12,"c":"BR"},{"i":11,"c":"TR"},{"i":11,"c":"MX"},{"c":"SV","i":9},{"i":9,"c":"BY"},{"i":8,"c":"MY"},{"c":"EC","i":8},{"i":7,"c":"LU"},{"c":"LT","i":7},{"i":6,"c":"EE"},{"c":"CO","i":6},{"c":"AR","i":6},{"i":5,"c":"TN"},{"c":"LV","i":5},{"c":"FO","i":5},{"i":4,"c":"PH"},{"c":"AE","i":4},{"i":3,"c":"MA"},{"i":3,"c":"ID"},{"c":"EG","i":3},{"c":"CR","i":3},{"c":"TG","i":2},{"c":"RE","i":2},{"c":"MT","i":2},{"i":2,"c":"MK"},{"c":"KZ","i":2},{"i":2,"c":"BA"},{"c":"AZ","i":2},{"c":"VG","i":1},{"i":1,"c":"UY"},{"i":1,"c":"TJ"},{"i":1,"c":"TC"},{"c":"RW","i":1},{"c":"QA","i":1},{"c":"PE","i":1},{"i":1,"c":"PA"},{"c":"OM","i":1},{"i":1,"c":"MU"},{"i":1,"c":"MQ"},{"i":1,"c":"MO"},{"i":1,"c":"IS"},{"c":"IR","i":1},{"i":1,"c":"DZ"},{"c":"CY","i":1},{"c":"CW","i":1},{"i":1,"c":"CD"},{"i":1,"c":"AX"}],"os":[{"c":1921,"o":"Debian (Docker) - x86_64"},{"o":"Windows (32-bit) - 8664","c":1572},{"o":"Debian - x86_64","c":1021},{"o":"piCore - aarch64","c":653},{"c":521,"o":"Debian - armv7l"},{"o":"Debian - aarch64","c":505},{"o":"Windows (64-bit) - 8664","c":498},{"o":"piCore - armv7l","c":441},{"c":322,"o":"macOS - x86_64"},{"o":"Debian (Docker) - aarch64","c":197},{"o":"macOS - arm64","c":76},{"o":"Windows (32-bit) - 586","c":67},{"c":63,"o":"Red Hat - x86_64"},{"c":63,"o":"macOS - x86_64 (Rosetta)"},{"o":"Debian (Docker) - armv7l","c":58},{"c":29,"o":"macOS - Unknown"},{"c":20,"o":"Linux - x86_64"},{"c":12,"o":"Debian (Android) - aarch64"},{"c":11,"o":"piCore - armv8l"},{"o":"SuSE - x86_64","c":10},{"c":8,"o":"Debian - i686"},{"o":"Alpine Linux - x86_64","c":7},{"o":"Others","c":30}],"playerTypes":[{"p":"Squeezelite","c":7912},{"c":3475,"p":"Squeezebox Radio"},{"p":"Squeezebox Touch","c":1443},{"p":"Squeezebox Boom","c":745},{"p":"Squeezebox Receiver","c":396},{"p":"Squeezebox 2/3/Classic","c":359},{"c":183,"p":"SqueezeESP32"},{"p":"SqueezePlay","c":105},{"c":96,"p":"Transporter"},{"c":46,"p":"Squeezebox Controller"},{"c":35,"p":"SqueezePlayer"},{"c":32,"p":"Daphile"},{"c":20,"p":"iPeng iPod"},{"c":18,"p":"iPeng iPad"},{"p":"HTTP","c":14},{"c":13,"p":"Squeezebox 1"},{"p":"Squeezeslave","c":5},{"p":"Squeeze Connect","c":5},{"c":3,"p":"SliMP3"},{"c":3,"p":"Euphony"},{"p":"Softsqueeze","c":2}]}