{"countries":[{"i":5668,"c":"DE"},{"i":3709,"c":"CN"},{"i":3366,"c":"US"},{"c":"FR","i":1970},{"i":1836,"c":"GB"},{"c":"NL","i":1629},{"c":"IT","i":1576},{"c":"CH","i":1012},{"c":"PL","i":763},{"i":748,"c":"JP"},{"i":698,"c":"CA"},{"c":"SE","i":636},{"i":572,"c":"RU"},{"c":"AT","i":536},{"i":506,"c":"BE"},{"i":409,"c":"AU"},{"c":"ES","i":338},{"c":"NO","i":315},{"c":"DK","i":285},{"c":"HK","i":284},{"c":"TW","i":249},{"i":212,"c":"CZ"},{"c":"RO","i":192},{"i":180,"c":"HU"},{"i":162,"c":"VN"},{"i":159,"c":"NZ"},{"c":"UA","i":141},{"c":"PT","i":120},{"i":112,"c":"FI"},{"c":"KR","i":108},{"i":103,"c":"SK"},{"i":102,"c":"GR"},{"i":96,"c":"HR"},{"i":96,"c":"BR"},{"i":95,"c":"IE"},{"c":"RS","i":87},{"i":84,"c":"TR"},{"i":81,"c":"SI"},{"c":"IN","i":70},{"c":"ZA","i":62},{"i":59,"c":"IL"},{"i":58,"c":"MX"},{"c":"AR","i":55},{"i":48,"c":"SG"},{"c":"BG","i":45},{"c":"CL","i":44},{"i":44,"c":"BY"},{"i":41,"c":"MY"},{"c":"LU","i":40},{"i":31,"c":"EE"},{"c":"CO","i":29},{"c":"TH","i":24},{"i":20,"c":"LV"},{"i":19,"c":"LT"},{"c":"BA","i":19},{"i":17,"c":"TN"},{"i":14,"c":"PH"},{"c":"XK","i":13},{"i":13,"c":"MQ"},{"c":"MK","i":13},{"i":11,"c":"ID"},{"c":"RE","i":10},{"i":10,"c":"AE"},{"i":8,"c":"MA"},{"i":8,"c":"EG"},{"c":"PY","i":7},{"c":"KZ","i":7},{"c":"IS","i":7},{"c":"UY","i":5},{"i":5,"c":"SA"},{"c":"GT","i":5},{"i":5,"c":"EC"},{"c":"CY","i":5},{"i":5,"c":"CR"},{"i":4,"c":"VE"},{"c":"UZ","i":4},{"i":4,"c":"PR"},{"i":4,"c":"NG"},{"i":4,"c":"MO"},{"i":4,"c":"IM"},{"i":4,"c":"FO"},{"i":4,"c":"CD"},{"i":4,"c":"AZ"},{"c":"TT","i":3},{"i":3,"c":"SV"},{"c":"PE","i":3},{"c":"PA","i":3},{"c":"NC","i":3},{"i":3,"c":"MU"},{"c":"MT","i":3},{"c":"MD","i":3},{"c":"LK","i":3},{"i":3,"c":"GG"},{"i":3,"c":"CV"},{"c":"BM","i":3},{"c":"AD","i":3},{"i":2,"c":"TG"},{"i":2,"c":"NP"},{"c":"LI","i":2},{"c":"JO","i":2},{"c":"JE","i":2},{"c":"IQ","i":2},{"c":"GH","i":2},{"i":2,"c":"DZ"},{"i":2,"c":"CG"},{"c":"AX","i":2},{"i":1,"c":"VG"},{"c":"TJ","i":1},{"c":"RW","i":1},{"c":"QA","i":1},{"i":1,"c":"PM"},{"i":1,"c":"PF"},{"i":1,"c":"MG"},{"i":1,"c":"ME"},{"i":1,"c":"MC"},{"c":"LY","i":1},{"i":1,"c":"KH"},{"c":"KE","i":1},{"c":"IR","i":1},{"i":1,"c":"GY"},{"i":1,"c":"GP"},{"i":1,"c":"GD"},{"i":1,"c":"DO"},{"c":"CW","i":1},{"c":"BO","i":1},{"c":"BH","i":1},{"c":"BD","i":1},{"i":1,"c":"AM"},{"i":1,"c":"AL"}],"versions":[{"v":"8.5.1","d":"2024-04-11","c":37},{"c":7,"d":"2024-04-11","v":"9.0.0"},{"d":"2024-04-11","v":"All","c":44},{"v":"8.5.1","d":"2024-04-12","c":61},{"v":"9.0.0","d":"2024-04-12","c":18},{"c":1,"v":"8.5.0","d":"2024-04-12"},{"d":"2024-04-12","v":"All","c":80},{"c":201,"d":"2024-04-13","v":"8.5.1"},{"c":75,"d":"2024-04-13","v":"9.0.0"},{"d":"2024-04-13","v":"8.5.0","c":1},{"c":277,"d":"2024-04-13","v":"All"},{"c":453,"v":"8.5.1","d":"2024-04-14"},{"c":154,"d":"2024-04-14","v":"9.0.0"},{"c":2,"d":"2024-04-14","v":"8.5.0"},{"d":"2024-04-14","v":"All","c":609},{"v":"8.5.1","d":"2024-04-15","c":922},{"c":306,"v":"9.0.0","d":"2024-04-15"},{"v":"8.5.2","d":"2024-04-15","c":73},{"v":"8.5.0","d":"2024-04-15","c":3},{"v":"All","d":"2024-04-15","c":1304},{"c":1408,"v":"8.5.1","d":"2024-04-16"},{"c":345,"d":"2024-04-16","v":"9.0.0"},{"d":"2024-04-16","v":"8.5.2","c":251},{"d":"2024-04-16","v":"8.5.0","c":4},{"c":2008,"v":"All","d":"2024-04-16"},{"c":2135,"d":"2024-04-17","v":"8.5.1"},{"c":406,"v":"9.0.0","d":"2024-04-17"},{"c":400,"d":"2024-04-17","v":"8.5.2"},{"d":"2024-04-17","v":"8.5.0","c":7},{"c":2948,"v":"All","d":"2024-04-17"},{"c":2685,"d":"2024-04-18","v":"8.5.1"},{"c":523,"v":"8.5.2","d":"2024-04-18"},{"d":"2024-04-18","v":"9.0.0","c":458},{"d":"2024-04-18","v":"8.5.0","c":9},{"c":3675,"d":"2024-04-18","v":"All"},{"c":3173,"v":"8.5.1","d":"2024-04-19"},{"v":"8.5.2","d":"2024-04-19","c":649},{"d":"2024-04-19","v":"9.0.0","c":487},{"c":13,"d":"2024-04-19","v":"8.5.0"},{"c":1,"d":"2024-04-19","v":"8.4.0"},{"v":"All","d":"2024-04-19","c":4323},{"v":"8.5.1","d":"2024-04-20","c":3629},{"v":"8.5.2","d":"2024-04-20","c":759},{"c":534,"v":"9.0.0","d":"2024-04-20"},{"c":19,"v":"8.5.0","d":"2024-04-20"},{"c":1,"d":"2024-04-20","v":"8.4.0"},{"d":"2024-04-20","v":"All","c":4942},{"v":"8.5.1","d":"2024-04-21","c":4194},{"c":882,"d":"2024-04-21","v":"8.5.2"},{"d":"2024-04-21","v":"9.0.0","c":574},{"c":23,"v":"8.5.0","d":"2024-04-21"},{"c":1,"d":"2024-04-21","v":"8.4.0"},{"c":5674,"d":"2024-04-21","v":"All"},{"c":4782,"v":"8.5.1","d":"2024-04-22"},{"v":"8.5.2","d":"2024-04-22","c":994},{"c":608,"v":"9.0.0","d":"2024-04-22"},{"c":31,"d":"2024-04-22","v":"8.5.0"},{"c":1,"d":"2024-04-22","v":"8.4.0"},{"v":"All","d":"2024-04-22","c":6416},{"c":5267,"d":"2024-04-23","v":"8.5.1"},{"c":1080,"d":"2024-04-23","v":"8.5.2"},{"d":"2024-04-23","v":"9.0.0","c":655},{"v":"8.5.0","d":"2024-04-23","c":31},{"d":"2024-04-23","v":"8.4.0","c":1},{"d":"2024-04-23","v":"All","c":7034},{"c":5691,"d":"2024-04-24","v":"8.5.1"},{"d":"2024-04-24","v":"8.5.2","c":1145},{"v":"9.0.0","d":"2024-04-24","c":690},{"d":"2024-04-24","v":"8.5.0","c":36},{"d":"2024-04-24","v":"8.4.0","c":2},{"d":"2024-04-24","v":"All","c":7564},{"d":"2024-04-25","v":"8.5.1","c":6106},{"v":"8.5.2","d":"2024-04-25","c":1216},{"v":"9.0.0","d":"2024-04-25","c":730},{"v":"8.5.0","d":"2024-04-25","c":40},{"d":"2024-04-25","v":"8.4.0","c":2},{"c":8094,"v":"All","d":"2024-04-25"},{"c":6536,"d":"2024-04-26","v":"8.5.1"},{"v":"8.5.2","d":"2024-04-26","c":1303},{"c":762,"d":"2024-04-26","v":"9.0.0"},{"c":44,"d":"2024-04-26","v":"8.5.0"},{"d":"2024-04-26","v":"8.4.0","c":2},{"c":1,"v":"8.4.1","d":"2024-04-26"},{"d":"2024-04-26","v":"All","c":8648},{"d":"2024-04-27","v":"8.5.1","c":7157},{"c":1504,"d":"2024-04-27","v":"8.5.2"},{"v":"9.0.0","d":"2024-04-27","c":797},{"c":44,"d":"2024-04-27","v":"8.5.0"},{"d":"2024-04-27","v":"8.4.0","c":2},{"d":"2024-04-27","v":"8.4.1","c":1},{"c":9505,"d":"2024-04-27","v":"All"},{"d":"2024-04-28","v":"8.5.1","c":7880},{"d":"2024-04-28","v":"8.5.2","c":1600},{"c":834,"d":"2024-04-28","v":"9.0.0"},{"c":45,"d":"2024-04-28","v":"8.5.0"},{"c":2,"d":"2024-04-28","v":"8.4.0"},{"c":1,"v":"8.4.1","d":"2024-04-28"},{"v":"All","d":"2024-04-28","c":10362},{"d":"2024-04-29","v":"8.5.1","c":8525},{"c":1695,"d":"2024-04-29","v":"8.5.2"},{"c":884,"d":"2024-04-29","v":"9.0.0"},{"v":"8.5.0","d":"2024-04-29","c":46},{"v":"8.4.0","d":"2024-04-29","c":3},{"c":1,"v":"8.4.1","d":"2024-04-29"},{"c":1,"v":"8.3.1","d":"2024-04-29"},{"c":11155,"d":"2024-04-29","v":"All"},{"c":8947,"v":"8.5.1","d":"2024-04-30"},{"c":1806,"d":"2024-04-30","v":"8.5.2"},{"c":928,"d":"2024-04-30","v":"9.0.0"},{"v":"8.5.0","d":"2024-04-30","c":46},{"d":"2024-04-30","v":"8.4.0","c":3},{"v":"8.4.1","d":"2024-04-30","c":2},{"v":"8.3.1","d":"2024-04-30","c":1},{"c":11733,"v":"All","d":"2024-04-30"},{"c":9313,"d":"2024-05-01","v":"8.5.1"},{"d":"2024-05-01","v":"8.5.2","c":1961},{"c":956,"v":"9.0.0","d":"2024-05-01"},{"v":"8.5.0","d":"2024-05-01","c":46},{"c":3,"v":"8.4.1","d":"2024-05-01"},{"c":3,"d":"2024-05-01","v":"8.4.0"},{"c":1,"v":"8.3.1","d":"2024-05-01"},{"c":12283,"v":"All","d":"2024-05-01"},{"d":"2024-05-02","v":"8.5.1","c":9800},{"c":2114,"v":"8.5.2","d":"2024-05-02"},{"c":990,"v":"9.0.0","d":"2024-05-02"},{"d":"2024-05-02","v":"8.5.0","c":48},{"c":4,"v":"8.4.1","d":"2024-05-02"},{"v":"8.4.0","d":"2024-05-02","c":4},{"c":1,"v":"8.3.1","d":"2024-05-02"},{"v":"All","d":"2024-05-02","c":12961},{"c":10123,"v":"8.5.1","d":"2024-05-03"},{"v":"8.5.2","d":"2024-05-03","c":2230},{"d":"2024-05-03","v":"9.0.0","c":1016},{"c":51,"v":"8.5.0","d":"2024-05-03"},{"c":4,"v":"8.4.1","d":"2024-05-03"},{"c":4,"v":"8.4.0","d":"2024-05-03"},{"c":1,"v":"8.3.1","d":"2024-05-03"},{"c":13429,"d":"2024-05-03","v":"All"},{"v":"8.5.1","d":"2024-05-04","c":10496},{"c":2367,"d":"2024-05-04","v":"8.5.2"},{"c":1052,"d":"2024-05-04","v":"9.0.0"},{"c":53,"d":"2024-05-04","v":"8.5.0"},{"v":"8.4.1","d":"2024-05-04","c":4},{"c":4,"d":"2024-05-04","v":"8.4.0"},{"d":"2024-05-04","v":"8.3.1","c":1},{"d":"2024-05-04","v":"All","c":13977},{"c":10914,"v":"8.5.1","d":"2024-05-05"},{"c":2479,"d":"2024-05-05","v":"8.5.2"},{"c":1090,"d":"2024-05-05","v":"9.0.0"},{"v":"8.5.0","d":"2024-05-05","c":55},{"c":4,"v":"8.4.1","d":"2024-05-05"},{"c":4,"v":"8.4.0","d":"2024-05-05"},{"d":"2024-05-05","v":"8.3.1","c":1},{"d":"2024-05-05","v":"All","c":14547},{"c":11394,"d":"2024-05-06","v":"8.5.1"},{"d":"2024-05-06","v":"8.5.2","c":2596},{"c":1124,"v":"9.0.0","d":"2024-05-06"},{"d":"2024-05-06","v":"8.5.0","c":59},{"c":4,"d":"2024-05-06","v":"8.4.1"},{"c":4,"v":"8.4.0","d":"2024-05-06"},{"d":"2024-05-06","v":"8.3.1","c":1},{"v":"All","d":"2024-05-06","c":15182},{"c":11706,"d":"2024-05-07","v":"8.5.1"},{"v":"8.5.2","d":"2024-05-07","c":2685},{"c":1155,"v":"9.0.0","d":"2024-05-07"},{"c":61,"d":"2024-05-07","v":"8.5.0"},{"c":4,"v":"8.4.1","d":"2024-05-07"},{"c":4,"v":"8.4.0","d":"2024-05-07"},{"v":"All","d":"2024-05-07","c":15615},{"c":12012,"d":"2024-05-08","v":"8.5.1"},{"v":"8.5.2","d":"2024-05-08","c":2777},{"v":"9.0.0","d":"2024-05-08","c":1175},{"c":63,"v":"8.5.0","d":"2024-05-08"},{"c":4,"v":"8.4.1","d":"2024-05-08"},{"v":"8.4.0","d":"2024-05-08","c":4},{"v":"All","d":"2024-05-08","c":16035},{"c":12306,"d":"2024-05-09","v":"8.5.1"},{"c":2876,"d":"2024-05-09","v":"8.5.2"},{"v":"9.0.0","d":"2024-05-09","c":1208},{"c":64,"d":"2024-05-09","v":"8.5.0"},{"v":"8.4.1","d":"2024-05-09","c":4},{"c":4,"v":"8.4.0","d":"2024-05-09"},{"c":16462,"v":"All","d":"2024-05-09"},{"v":"8.5.1","d":"2024-05-10","c":12636},{"c":3260,"d":"2024-05-10","v":"8.5.2"},{"c":1219,"v":"9.0.0","d":"2024-05-10"},{"c":65,"v":"8.5.0","d":"2024-05-10"},{"c":4,"d":"2024-05-10","v":"8.4.1"},{"c":4,"d":"2024-05-10","v":"8.4.0"},{"d":"2024-05-10","v":"All","c":17188},{"v":"8.5.1","d":"2024-05-11","c":12962},{"d":"2024-05-11","v":"8.5.2","c":3859},{"c":1238,"v":"9.0.0","d":"2024-05-11"},{"d":"2024-05-11","v":"8.5.0","c":67},{"c":4,"d":"2024-05-11","v":"8.4.1"},{"d":"2024-05-11","v":"8.4.0","c":4},{"d":"2024-05-11","v":"All","c":18134},{"c":13234,"v":"8.5.1","d":"2024-05-12"},{"c":4232,"d":"2024-05-12","v":"8.5.2"},{"v":"9.0.0","d":"2024-05-12","c":1255},{"c":70,"v":"8.5.0","d":"2024-05-12"},{"d":"2024-05-12","v":"8.4.1","c":4},{"c":4,"v":"8.4.0","d":"2024-05-12"},{"c":18799,"v":"All","d":"2024-05-12"},{"c":13588,"v":"8.5.1","d":"2024-05-13"},{"c":4711,"d":"2024-05-13","v":"8.5.2"},{"d":"2024-05-13","v":"9.0.0","c":1292},{"c":69,"v":"8.5.0","d":"2024-05-13"},{"d":"2024-05-13","v":"8.4.1","c":4},{"v":"8.4.0","d":"2024-05-13","c":4},{"d":"2024-05-13","v":"All","c":19668},{"c":13839,"v":"8.5.1","d":"2024-05-14"},{"c":5074,"v":"8.5.2","d":"2024-05-14"},{"c":1309,"v":"9.0.0","d":"2024-05-14"},{"c":70,"v":"8.5.0","d":"2024-05-14"},{"d":"2024-05-14","v":"8.4.1","c":4},{"c":4,"d":"2024-05-14","v":"8.4.0"},{"v":"All","d":"2024-05-14","c":20300},{"c":14087,"d":"2024-05-15","v":"8.5.1"},{"d":"2024-05-15","v":"8.5.2","c":5460},{"v":"9.0.0","d":"2024-05-15","c":1325},{"v":"8.5.0","d":"2024-05-15","c":71},{"d":"2024-05-15","v":"8.4.1","c":4},{"c":4,"d":"2024-05-15","v":"8.4.0"},{"c":20951,"d":"2024-05-15","v":"All"},{"c":14280,"v":"8.5.1","d":"2024-05-16"},{"c":5829,"d":"2024-05-16","v":"8.5.2"},{"c":1338,"v":"9.0.0","d":"2024-05-16"},{"c":79,"d":"2024-05-16","v":"8.5.0"},{"v":"8.4.1","d":"2024-05-16","c":5},{"d":"2024-05-16","v":"8.4.0","c":4},{"c":21535,"v":"All","d":"2024-05-16"},{"c":14412,"d":"2024-05-17","v":"8.5.1"},{"d":"2024-05-17","v":"8.5.2","c":6118},{"c":1357,"d":"2024-05-17","v":"9.0.0"},{"c":81,"v":"8.5.0","d":"2024-05-17"},{"d":"2024-05-17","v":"8.4.1","c":5},{"c":4,"d":"2024-05-17","v":"8.4.0"},{"v":"All","d":"2024-05-17","c":21977},{"v":"8.5.1","d":"2024-05-18","c":14622},{"c":6440,"v":"8.5.2","d":"2024-05-18"},{"c":1377,"v":"9.0.0","d":"2024-05-18"},{"c":84,"d":"2024-05-18","v":"8.5.0"},{"c":5,"d":"2024-05-18","v":"8.4.1"},{"d":"2024-05-18","v":"8.4.0","c":4},{"c":22532,"v":"All","d":"2024-05-18"},{"c":14853,"v":"8.5.1","d":"2024-05-19"},{"v":"8.5.2","d":"2024-05-19","c":6786},{"v":"9.0.0","d":"2024-05-19","c":1402},{"c":85,"v":"8.5.0","d":"2024-05-19"},{"v":"8.4.1","d":"2024-05-19","c":5},{"v":"8.4.0","d":"2024-05-19","c":5},{"c":23136,"d":"2024-05-19","v":"All"},{"c":15041,"v":"8.5.1","d":"2024-05-20"},{"c":7157,"d":"2024-05-20","v":"8.5.2"},{"c":1429,"v":"9.0.0","d":"2024-05-20"},{"d":"2024-05-20","v":"8.5.0","c":84},{"v":"8.4.1","d":"2024-05-20","c":5},{"d":"2024-05-20","v":"8.4.0","c":5},{"d":"2024-05-20","v":"All","c":23721},{"d":"2024-05-21","v":"8.5.1","c":15199},{"v":"8.5.2","d":"2024-05-21","c":7400},{"c":1452,"d":"2024-05-21","v":"9.0.0"},{"c":84,"d":"2024-05-21","v":"8.5.0"},{"c":6,"d":"2024-05-21","v":"8.4.0"},{"c":5,"v":"8.4.1","d":"2024-05-21"},{"c":24146,"d":"2024-05-21","v":"All"},{"c":15262,"v":"8.5.1","d":"2024-05-22"},{"d":"2024-05-22","v":"8.5.2","c":7641},{"c":1468,"v":"9.0.0","d":"2024-05-22"},{"v":"8.5.0","d":"2024-05-22","c":85},{"v":"8.4.0","d":"2024-05-22","c":6},{"c":5,"d":"2024-05-22","v":"8.4.1"},{"c":24467,"v":"All","d":"2024-05-22"},{"c":15374,"d":"2024-05-23","v":"8.5.1"},{"c":7904,"d":"2024-05-23","v":"8.5.2"},{"v":"9.0.0","d":"2024-05-23","c":1490},{"c":87,"d":"2024-05-23","v":"8.5.0"},{"v":"8.4.0","d":"2024-05-23","c":6},{"v":"8.4.1","d":"2024-05-23","c":5},{"v":"All","d":"2024-05-23","c":24866},{"d":"2024-05-24","v":"8.5.1","c":15441},{"c":8140,"v":"8.5.2","d":"2024-05-24"},{"c":1513,"d":"2024-05-24","v":"9.0.0"},{"c":86,"v":"8.5.0","d":"2024-05-24"},{"d":"2024-05-24","v":"8.4.1","c":5},{"c":5,"v":"8.4.0","d":"2024-05-24"},{"d":"2024-05-24","v":"All","c":25190},{"c":15556,"v":"8.5.1","d":"2024-05-25"},{"v":"8.5.2","d":"2024-05-25","c":8386},{"v":"9.0.0","d":"2024-05-25","c":1532},{"c":83,"v":"8.5.0","d":"2024-05-25"},{"v":"8.4.1","d":"2024-05-25","c":5},{"c":5,"v":"8.4.0","d":"2024-05-25"},{"c":25567,"d":"2024-05-25","v":"All"},{"d":"2024-05-26","v":"8.5.1","c":15649},{"v":"8.5.2","d":"2024-05-26","c":8622},{"v":"9.0.0","d":"2024-05-26","c":1557},{"c":82,"v":"8.5.0","d":"2024-05-26"},{"c":5,"d":"2024-05-26","v":"8.4.1"},{"c":5,"v":"8.4.0","d":"2024-05-26"},{"c":25920,"v":"All","d":"2024-05-26"},{"c":15408,"v":"8.5.1","d":"2024-05-27"},{"c":9105,"d":"2024-05-27","v":"8.5.2"},{"c":1578,"v":"9.0.0","d":"2024-05-27"},{"c":92,"d":"2024-05-27","v":"8.5.3"},{"c":83,"v":"8.5.0","d":"2024-05-27"},{"c":5,"d":"2024-05-27","v":"8.4.1"},{"c":5,"d":"2024-05-27","v":"8.4.0"},{"c":26276,"d":"2024-05-27","v":"All"},{"d":"2024-05-28","v":"8.5.1","c":14582},{"d":"2024-05-28","v":"8.5.2","c":9926},{"c":1579,"d":"2024-05-28","v":"9.0.0"},{"c":406,"v":"8.5.3","d":"2024-05-28"},{"d":"2024-05-28","v":"8.5.0","c":83},{"c":5,"v":"8.4.1","d":"2024-05-28"},{"c":5,"v":"8.4.0","d":"2024-05-28"},{"v":"All","d":"2024-05-28","c":26586},{"c":14085,"v":"8.5.1","d":"2024-05-29"},{"c":10544,"v":"8.5.2","d":"2024-05-29"},{"c":1579,"d":"2024-05-29","v":"9.0.0"},{"v":"8.5.3","d":"2024-05-29","c":551},{"v":"8.5.0","d":"2024-05-29","c":84},{"c":5,"v":"8.4.1","d":"2024-05-29"},{"d":"2024-05-29","v":"8.4.0","c":5},{"c":26853,"d":"2024-05-29","v":"All"},{"d":"2024-05-30","v":"8.5.1","c":13718},{"v":"8.5.2","d":"2024-05-30","c":11094},{"v":"9.0.0","d":"2024-05-30","c":1579},{"c":653,"v":"8.5.3","d":"2024-05-30"},{"v":"8.5.0","d":"2024-05-30","c":85},{"d":"2024-05-30","v":"8.4.1","c":5},{"d":"2024-05-30","v":"8.4.0","c":5},{"v":"All","d":"2024-05-30","c":27139},{"c":13381,"d":"2024-05-31","v":"8.5.1"},{"v":"8.5.2","d":"2024-05-31","c":11685},{"d":"2024-05-31","v":"9.0.0","c":1577},{"c":747,"d":"2024-05-31","v":"8.5.3"},{"d":"2024-05-31","v":"8.5.0","c":82},{"d":"2024-05-31","v":"8.4.1","c":5},{"d":"2024-05-31","v":"8.4.0","c":5},{"c":27482,"d":"2024-05-31","v":"All"},{"c":12747,"d":"2024-06-01","v":"8.5.1"},{"v":"8.5.2","d":"2024-06-01","c":12540},{"v":"9.0.0","d":"2024-06-01","c":1596},{"d":"2024-06-01","v":"8.5.3","c":842},{"c":80,"d":"2024-06-01","v":"8.5.0"},{"v":"8.4.1","d":"2024-06-01","c":5},{"d":"2024-06-01","v":"8.4.0","c":5},{"d":"2024-06-01","v":"All","c":27815},{"d":"2024-06-02","v":"8.5.2","c":13489},{"c":12160,"v":"8.5.1","d":"2024-06-02"},{"v":"9.0.0","d":"2024-06-02","c":1609},{"c":929,"d":"2024-06-02","v":"8.5.3"},{"d":"2024-06-02","v":"8.5.0","c":80},{"c":5,"v":"8.4.1","d":"2024-06-02"},{"c":5,"v":"8.4.0","d":"2024-06-02"},{"d":"2024-06-02","v":"All","c":28277},{"c":14095,"d":"2024-06-03","v":"8.5.2"},{"c":11850,"v":"8.5.1","d":"2024-06-03"},{"d":"2024-06-03","v":"9.0.0","c":1613},{"c":1027,"v":"8.5.3","d":"2024-06-03"},{"d":"2024-06-03","v":"8.5.0","c":83},{"c":5,"v":"8.4.1","d":"2024-06-03"},{"d":"2024-06-03","v":"8.4.0","c":5},{"d":"2024-06-03","v":"All","c":28678},{"v":"8.5.2","d":"2024-06-04","c":14600},{"d":"2024-06-04","v":"8.5.1","c":11533},{"d":"2024-06-04","v":"9.0.0","c":1612},{"d":"2024-06-04","v":"8.5.3","c":1088},{"c":84,"v":"8.5.0","d":"2024-06-04"},{"d":"2024-06-04","v":"8.4.1","c":5},{"c":5,"d":"2024-06-04","v":"8.4.0"},{"c":28927,"d":"2024-06-04","v":"All"},{"v":"8.5.2","d":"2024-06-05","c":15028},{"c":11214,"v":"8.5.1","d":"2024-06-05"},{"c":1605,"d":"2024-06-05","v":"9.0.0"},{"c":1133,"d":"2024-06-05","v":"8.5.3"},{"d":"2024-06-05","v":"8.5.0","c":84},{"c":5,"v":"8.4.1","d":"2024-06-05"},{"v":"8.4.0","d":"2024-06-05","c":5},{"v":"All","d":"2024-06-05","c":29074},{"v":"8.5.2","d":"2024-06-06","c":15432},{"c":10992,"v":"8.5.1","d":"2024-06-06"},{"v":"9.0.0","d":"2024-06-06","c":1608},{"d":"2024-06-06","v":"8.5.3","c":1196},{"c":85,"v":"8.5.0","d":"2024-06-06"},{"v":"8.4.1","d":"2024-06-06","c":5},{"d":"2024-06-06","v":"8.4.0","c":5},{"c":29323,"d":"2024-06-06","v":"All"},{"c":15834,"d":"2024-06-07","v":"8.5.2"},{"v":"8.5.1","d":"2024-06-07","c":10779},{"c":1614,"d":"2024-06-07","v":"9.0.0"},{"v":"8.5.3","d":"2024-06-07","c":1253},{"c":86,"v":"8.5.0","d":"2024-06-07"},{"c":5,"v":"8.4.1","d":"2024-06-07"},{"c":5,"v":"8.4.0","d":"2024-06-07"},{"d":"2024-06-07","v":"All","c":29576},{"c":16206,"v":"8.5.2","d":"2024-06-08"},{"v":"8.5.1","d":"2024-06-08","c":10560},{"d":"2024-06-08","v":"9.0.0","c":1610},{"c":1364,"d":"2024-06-08","v":"8.5.3"},{"c":86,"d":"2024-06-08","v":"8.5.0"},{"d":"2024-06-08","v":"8.4.1","c":5},{"c":5,"v":"8.4.0","d":"2024-06-08"},{"v":"All","d":"2024-06-08","c":29836},{"c":16527,"v":"8.5.2","d":"2024-06-09"},{"c":10358,"v":"8.5.1","d":"2024-06-09"},{"c":1614,"d":"2024-06-09","v":"9.0.0"},{"c":1471,"v":"8.5.3","d":"2024-06-09"},{"v":"8.5.0","d":"2024-06-09","c":90},{"v":"8.4.1","d":"2024-06-09","c":5},{"c":5,"d":"2024-06-09","v":"8.4.0"},{"c":30070,"v":"All","d":"2024-06-09"},{"d":"2024-06-10","v":"8.5.2","c":16802},{"c":10154,"v":"8.5.1","d":"2024-06-10"},{"c":1617,"v":"9.0.0","d":"2024-06-10"},{"v":"8.5.3","d":"2024-06-10","c":1568},{"c":90,"d":"2024-06-10","v":"8.5.0"},{"d":"2024-06-10","v":"8.4.1","c":5},{"d":"2024-06-10","v":"8.4.0","c":5},{"v":"All","d":"2024-06-10","c":30241},{"v":"8.5.2","d":"2024-06-11","c":16943},{"c":9943,"d":"2024-06-11","v":"8.5.1"},{"v":"8.5.3","d":"2024-06-11","c":1662},{"c":1618,"d":"2024-06-11","v":"9.0.0"},{"d":"2024-06-11","v":"8.5.0","c":91},{"d":"2024-06-11","v":"8.4.1","c":5},{"c":5,"v":"8.4.0","d":"2024-06-11"},{"v":"All","d":"2024-06-11","c":30267},{"c":16846,"v":"8.5.2","d":"2024-06-12"},{"c":9713,"d":"2024-06-12","v":"8.5.1"},{"d":"2024-06-12","v":"8.5.3","c":1949},{"v":"9.0.0","d":"2024-06-12","c":1617},{"d":"2024-06-12","v":"8.5.0","c":92},{"v":"8.4.0","d":"2024-06-12","c":5},{"c":4,"v":"8.4.1","d":"2024-06-12"},{"v":"All","d":"2024-06-12","c":30226}],"connectedPlayers":[{"c":11376,"p":"1"},{"c":6353,"p":"0"},{"c":5218,"p":"2"},{"p":"3","c":2560},{"c":1569,"p":"4"},{"c":963,"p":"5"},{"p":"6","c":632},{"p":"7","c":455},{"p":"8","c":290},{"p":"9","c":206},{"p":"10","c":176},{"p":"11","c":115},{"c":85,"p":"12"},{"p":"13","c":57},{"p":"14","c":44},{"c":27,"p":"15"},{"p":"17","c":19},{"p":"16","c":18},{"p":"18","c":13},{"p":"19","c":9},{"c":7,"p":"23"},{"c":7,"p":"20"},{"c":6,"p":"21"},{"p":"24","c":5},{"c":5,"p":"22"},{"c":3,"p":"25"},{"c":2,"p":"26"},{"c":1,"p":"51"},{"c":1,"p":"44"},{"c":1,"p":"43"},{"c":1,"p":"36"},{"p":"33","c":1},{"p":"32","c":1},{"c":1,"p":"31"},{"c":1,"p":"30"},{"c":1,"p":"27"}],"tracks":[{"c":10091,"t":"0"},{"t":"1","c":4581},{"t":"500","c":1199},{"c":4053,"t":"1000"},{"t":"5000","c":2669},{"t":"10000","c":2969},{"c":2802,"t":"20000"},{"c":1145,"t":"50000"},{"t":"100000","c":694},{"c":18,"t":"500000"},{"t":"1000000","c":8}],"os":[{"c":7797,"o":"Daphile - x86_64"},{"o":"Debian (Docker) - x86_64","c":4445},{"c":3375,"o":"Windows (32-bit) - 8664"},{"c":2416,"o":"Debian - x86_64"},{"o":"Windows (64-bit) - 8664","c":2328},{"c":1928,"o":"piCore - aarch64"},{"o":"piCore - armv7l","c":1368},{"c":1199,"o":"Debian - aarch64"},{"o":"Debian - armv7l","c":1186},{"c":967,"o":"Debian (Docker) - aarch64"},{"c":731,"o":"macOS - x86_64"},{"c":600,"o":"Daphile - i686"},{"o":"QLMS 2.X [Debian] - x86_64","c":437},{"c":257,"o":"macOS - arm64"},{"c":249,"o":"Red Hat - x86_64"},{"o":"macOS - x86_64 (Rosetta)","c":159},{"c":144,"o":"Windows (32-bit) - 586"},{"o":"Debian (Docker) - armv7l","c":125},{"o":"Linux - x86_64","c":118},{"c":54,"o":"QLMS 2.X [Debian] - aarch64"},{"c":52,"o":"FreeBSD - amd64-freebsd"},{"c":48,"o":"QLMS 2.X [Debian] - armv7l"},{"o":"Debian (Android) - aarch64","c":44},{"o":"QLMS 2.X [Debian] - i686","c":25},{"o":"macOS - Unknown","c":24},{"c":20,"o":"piCore - armv8l"},{"c":19,"o":"SuSE - x86_64"},{"o":"Linux - aarch64","c":17},{"o":"Debian - i686","c":16},{"o":"Debian (Android) - armv7l","c":15},{"c":11,"o":"QLMS 2.X [Debian] - armv5tel"},{"o":"Alpine Linux - x86_64","c":10},{"o":"Gentoo Linux - x86_64","c":9},{"c":8,"o":"freebsd - amd64-freebsd"},{"c":4,"o":"Linux - armv5tel"},{"c":4,"o":"Linux - i686"},{"c":3,"o":"Alpine Linux - aarch64"},{"c":3,"o":"Debian - riscv64"},{"o":"Linux - armv7l","c":3},{"o":"Red Hat - aarch64","c":3},{"o":"Debian - armv8l","c":2},{"o":"Gentoo Linux - armv5tel","c":2},{"c":1,"o":"Linux (optware-ng) - armv5eabi-legacy"},{"c":1,"o":"SSOTS 4.x (QNAP TurboStation) - i686"},{"o":"SuSE - aarch64","c":1},{"o":"openbsd - amd64-openbsd","c":1}],"playerTypes":[{"p":"Squeezelite","c":16817},{"p":"Daphile","c":10442},{"p":"Squeezebox Radio","c":9559},{"p":"Squeezebox Touch","c":3494},{"p":"UPnPBridge","c":2851},{"p":"Unknown","c":2810},{"c":2528,"p":"CastBridge"},{"c":2235,"p":"RaopBridge"},{"c":1907,"p":"Squeezebox Boom"},{"c":1148,"p":"Squeezebox Receiver"},{"c":942,"p":"Squeezebox 2/3/Classic"},{"p":"SqueezePlay","c":765},{"c":682,"p":"SqueezeLite-pCP"},{"p":"SqueezeESP32","c":588},{"c":541,"p":"Squeezelite-X"},{"c":531,"p":"MusicServer4(Home|Loxone)"},{"c":295,"p":"Transporter"},{"p":"SqueezePlayer","c":247},{"c":141,"p":"SB Player"},{"p":"SqueezeLite-HA-Addon","c":126},{"c":119,"p":"HiFiBerry"},{"c":117,"p":"Squeezebox Controller"},{"c":93,"p":"Web Client"},{"p":"SqueezeLiteBT","c":86},{"p":"SqueezePad","c":78},{"c":47,"p":"Denon/Marantz AVR"},{"c":43,"p":"Ropieee"},{"c":37,"p":"HTTP"},{"c":33,"p":"Squeezebox 1"},{"p":"Softsqueeze","c":21},{"p":"SqueezeLiteBT-pCP","c":19},{"c":19,"p":"DMP-A6"},{"p":"iPeng iPhone","c":18},{"p":"SqueezeLiteAndroid","c":17},{"c":15,"p":"SqueezeLite-R2"},{"c":14,"p":"iPeng iPad"},{"p":"SliMP3","c":13},{"c":10,"p":"Squeezeslave"},{"p":"GentooPlayer","c":9},{"p":"AroioOS","c":9},{"c":7,"p":"SqueezeLiteTTS"},{"p":"RaspberryPi","c":7},{"c":7,"p":"Kodi"},{"p":"Str@mbo","c":6},{"c":6,"p":"Squeeze Connect"},{"c":6,"p":"OLADRAplayer"},{"c":6,"p":"AVE"},{"c":4,"p":"SqueezeWRT"},{"p":"OpenFrame","c":4},{"p":"K50player","c":4},{"p":"TonyDS3","c":3},{"c":3,"p":"SlimLibrary"},{"p":"LARA","c":3},{"c":3,"p":"K22"},{"p":"Denon Home 150L (RHEOS: Denon Home 150)","c":3},{"p":"Denon AVR-X4300H (RHEOS: Denon AVR-X4300H)","c":3},{"c":2,"p":"SqueezeLiteWin"},{"p":"Raspberry Pi4b Rev1.5 8GB","c":2},{"c":2,"p":"Pure_192.168.1.20"},{"c":2,"p":"PiCorePlayer"},{"p":"OrangePi Plus2E","c":2},{"c":2,"p":"Living Room 2 (RHEOS: HEOS 3)"},{"c":2,"p":"Living Room 1 (RHEOS: HEOS 3)"},{"c":2,"p":"Kitchen HiFi"},{"c":2,"p":"K21"},{"p":"G1K50player","c":2},{"c":2,"p":"DMP-A8"},{"p":"Denon LivingRoom AVR-X4500H (RHEOS: Denon AVR-X4500H)","c":2},{"p":"Denon Home 150R (RHEOS: Denon Home 150)","c":2},{"c":2,"p":"Companion"},{"c":2,"p":"Antipodes"},{"c":2,"p":"Yulong"},{"p":"Topping","c":2},{"c":1,"p":"USB"},{"c":1,"p":"Suptronics-x400v3"},{"p":"Sugarcube","c":1},{"c":1,"p":"StylusEP"},{"p":"Stereo [USB]","c":1},{"p":"SqueezeLiteFedora","c":1},{"c":1,"p":"SqueezeLite-pCP-pCP-pCP-pCP-pCP-pCP-pCP-pCP-pCP-pCP-pCP"},{"c":1,"p":"SqueezeCore"},{"p":"SQL_Spring3","c":1},{"p":"Sorcere","c":1},{"p":"Sa-link [LINK]","c":1},{"p":"Raspberry Pi4b Rev1.5 4GB","c":1},{"c":1,"p":"Radio"},{"c":1,"p":"Pure_192.168.62.57"},{"p":"Pure_192.168.2.101","c":1},{"c":1,"p":"Pure_192.168.1.84"},{"c":1,"p":"NONE"},{"c":1,"p":"Narbondel"},{"c":1,"p":"MWieza"},{"c":1,"p":"MSZ [Squeezelite]"},{"c":1,"p":"MLazienka"},{"p":"MKuchnia","c":1},{"c":1,"p":"Metrum Ambre"},{"p":"MDzieci","c":1},{"p":"MDPokoj","c":1},{"c":1,"p":"M6 Encore"},{"p":"LucasAudioLabs","c":1},{"p":"LinQ","c":1},{"p":"Link [LINK]","c":1},{"p":"LAZZARI","c":1},{"c":1,"p":"HEOS 5 (RHEOS: HEOS 5)"},{"c":1,"p":"Fardrimm"},{"p":"ExtremeDirect-NS","c":1},{"c":1,"p":"Dolblunde"},{"p":"Denon AVC-X8500H (RHEOS: Denon AVC-X8500H)","c":1},{"p":"Couisine","c":1},{"p":"Bedroom Stereo","c":1}],"players":[{"p":127,"d":"2024-04-11"},{"d":"2024-04-12","p":50},{"p":925,"d":"2024-04-13"},{"p":1838,"d":"2024-04-14"},{"d":"2024-04-15","p":3339},{"d":"2024-04-16","p":4696},{"d":"2024-04-17","p":6497},{"d":"2024-04-18","p":7871},{"p":9016,"d":"2024-04-19"},{"p":10086,"d":"2024-04-20"},{"d":"2024-04-21","p":11382},{"p":12499,"d":"2024-04-22"},{"d":"2024-04-23","p":13333},{"p":14261,"d":"2024-04-24"},{"d":"2024-04-25","p":14916},{"p":15712,"d":"2024-04-26"},{"d":"2024-04-27","p":17074},{"p":18319,"d":"2024-04-28"},{"d":"2024-04-29","p":19596},{"p":20517,"d":"2024-04-30"},{"p":21345,"d":"2024-05-01"},{"p":22303,"d":"2024-05-02"},{"p":22962,"d":"2024-05-03"},{"d":"2024-05-04","p":23757},{"d":"2024-05-05","p":24536},{"p":25439,"d":"2024-05-06"},{"p":26024,"d":"2024-05-07"},{"d":"2024-05-08","p":26546},{"p":27088,"d":"2024-05-09"},{"p":28784,"d":"2024-05-10"},{"p":30710,"d":"2024-05-11"},{"d":"2024-05-12","p":32036},{"p":33639,"d":"2024-05-13"},{"d":"2024-05-14","p":34811},{"d":"2024-05-15","p":35865},{"d":"2024-05-16","p":37094},{"p":38044,"d":"2024-05-17"},{"d":"2024-05-18","p":39082},{"p":40228,"d":"2024-05-19"},{"p":41472,"d":"2024-05-20"},{"d":"2024-05-21","p":42215},{"d":"2024-05-22","p":42893},{"p":43729,"d":"2024-05-23"},{"d":"2024-05-24","p":44226},{"p":44903,"d":"2024-05-25"},{"p":45767,"d":"2024-05-26"},{"d":"2024-05-27","p":46551},{"d":"2024-05-28","p":47850},{"p":48860,"d":"2024-05-29"},{"p":49944,"d":"2024-05-30"},{"p":51173,"d":"2024-05-31"},{"p":52443,"d":"2024-06-01"},{"d":"2024-06-02","p":53905},{"p":55102,"d":"2024-06-03"},{"d":"2024-06-04","p":56027},{"d":"2024-06-05","p":56515},{"d":"2024-06-06","p":57121},{"d":"2024-06-07","p":57646},{"p":58226,"d":"2024-06-08"},{"d":"2024-06-09","p":58828},{"p":59239,"d":"2024-06-10"},{"p":59504,"d":"2024-06-11"},{"d":"2024-06-12","p":59623}]}