[{"Language": "Czech", "Identifier": "CS", "Coverage": 97.98165137614679}, {"Language": "German", "Identifier": "DE", "Coverage": 97.5229357798165}, {"Language": "English", "Identifier": "EN", "Coverage": 100.0}, {"Language": "French", "Identifier": "FR", "Coverage": 99.31192660550458}, {"Language": "Hungarian", "Identifier": "HU", "Coverage": 98.57798165137615}, {"Language": "Dutch", "Identifier": "NL", "Coverage": 97.43119266055047}, {"Language": "Norwegian", "Identifier": "NO", "Coverage": 90.27522935779817}, {"Language": "Polish", "Identifier": "PL", "Coverage": 89.63302752293578}, {"Language": "Swedish", "Identifier": "SV", "Coverage": 91.97247706422019}, {"Language": "Danish", "Identifier": "DA", "Coverage": 85.0}, {"Language": "Spanish", "Identifier": "ES", "Coverage": 85.96330275229357}, {"Language": "Finnish", "Identifier": "FI", "Coverage": 84.58715596330275}, {"Language": "Hebrew", "Identifier": "HE", "Coverage": 43.944954128440365}, {"Language": "Italian", "Identifier": "IT", "Coverage": 84.77064220183486}, {"Language": "Russian", "Identifier": "RU", "Coverage": 84.31192660550458}, {"Language": "Chinese (Simplified, China)", "Identifier": "ZH_CN", "Coverage": 44.357798165137616}, {"Language": "Japanese", "Identifier": "JA", "Coverage": 23.486238532110093}, {"Language": "Portuguese", "Identifier": "PT", "Coverage": 16.880733944954127}, {"Language": "English (United Kingdom)", "Identifier": "EN_GB", "Coverage": 2.981651376146789}]
